timeseries/__init__.py
timeseries/main.py
time_series-0.2.dist-info/LICENSE
time_series-0.2.dist-info/METADATA
time_series-0.2.dist-info/WHEEL
time_series-0.2.dist-info/top_level.txt
time_series-0.2.dist-info/RECORD
