Metadata-Version: 2.1
Name: time-series
Version: 0.2
Summary: Python implementation of a sliding window.
Home-page: https://github.com/ani071/timeseries
Author: Andreas Isnes Nilsen
Author-email: andnil94@gmail.com
License: UNKNOWN
Keywords: window,time,series
Platform: UNKNOWN
Classifier: Programming Language :: Python :: 3
Classifier: License :: OSI Approved :: MIT License
Classifier: Operating System :: OS Independent
